falconcore_agent/__init__.py
falconcore_agent/main.py
falconcore_agent-2.1.1.dist-info/licenses/LICENSE
falconcore_agent-2.1.1.dist-info/METADATA
falconcore_agent-2.1.1.dist-info/WHEEL
falconcore_agent-2.1.1.dist-info/top_level.txt
falconcore_agent-2.1.1.dist-info/RECORD
