Metadata-Version: 2.4
Name: falconcore-agent
Version: 2.1.1
Summary: Enterprise cybersecurity threat intelligence agent with system tray integration
Author-email: Your Name <your.email@example.com>
License: MIT
Project-URL: Homepage, https://github.com/yourusername/falconcore-agent
Project-URL: Documentation, https://github.com/yourusername/falconcore-agent#readme
Project-URL: Repository, https://github.com/yourusername/falconcore-agent
Project-URL: Bug Tracker, https://github.com/yourusername/falconcore-agent/issues
Keywords: cybersecurity,threat-intelligence,security-agent,system-tray,malware-detection
Classifier: Development Status :: 4 - Beta
Classifier: Intended Audience :: System Administrators
Classifier: Intended Audience :: Information Technology
Classifier: Topic :: Security
Classifier: Topic :: System :: Monitoring
Classifier: Topic :: System :: Systems Administration
Classifier: License :: OSI Approved :: MIT License
Classifier: Programming Language :: Python :: 3
Classifier: Programming Language :: Python :: 3.8
Classifier: Programming Language :: Python :: 3.9
Classifier: Programming Language :: Python :: 3.10
Classifier: Programming Language :: Python :: 3.11
Classifier: Programming Language :: Python :: 3.12
Classifier: Operating System :: OS Independent
Classifier: Operating System :: Microsoft :: Windows
Classifier: Operating System :: POSIX :: Linux
Classifier: Operating System :: MacOS
Requires-Python: >=3.8
License-File: LICENSE
Requires-Dist: requests>=2.25.0
Requires-Dist: psutil>=5.8.0
Requires-Dist: packaging>=21.0
Requires-Dist: opentelemetry-api>=1.12.0
Requires-Dist: opentelemetry-sdk>=1.12.0
Requires-Dist: opentelemetry-exporter-jaeger-thrift>=1.12.0
Requires-Dist: opentelemetry-instrumentation-requests>=0.33b0
Provides-Extra: gui
Requires-Dist: pystray>=0.19.0; extra == "gui"
Requires-Dist: pillow>=8.0.0; extra == "gui"
Provides-Extra: macos
Requires-Dist: rumps>=0.3.0; extra == "macos"
Dynamic: license-file
